PyMediaTools/PyMediaTools.py
PyMediaTools/__init__.py
PyMediaTools-1.0.0.dist-info/METADATA
PyMediaTools-1.0.0.dist-info/WHEEL
PyMediaTools-1.0.0.dist-info/top_level.txt
PyMediaTools-1.0.0.dist-info/RECORD
