Metadata-Version: 2.1
Name: PyMediaTools
Version: 1.0.0
Summary: A library to read video and audio files
Home-page: https://github.com/zinzied/PyMediaTools
Author: Zied Boughdir
Author-email: ziedboughdir@gmail.com
Classifier: Programming Language :: Python :: 3
Classifier: License :: OSI Approved :: MIT License
Classifier: Operating System :: OS Independent
Requires-Dist: moviepy
Requires-Dist: pydub
